heartbridge/__init__.py
heartbridge/__main__.py
heartbridge/app.py
heartbridge/constants.py
heartbridge/data.py
heartbridge/exception_handlers.py
heartbridge/exceptions.py
heartbridge/export.py
heartbridge/health.py
heartbridge/heart.py
heartbridge/server.py
heartbridge-2.0.0.dist-info/LICENSE
heartbridge-2.0.0.dist-info/METADATA
heartbridge-2.0.0.dist-info/WHEEL
heartbridge-2.0.0.dist-info/entry_points.txt
heartbridge-2.0.0.dist-info/top_level.txt
heartbridge-2.0.0.dist-info/RECORD
