Metadata-Version: 2.1
Name: heartbridge
Version: 2.0.0
Summary: Command line tool to transfer heart rate and other data from iOS Health to your computer. Works with a companion iOS shortcut.
Home-page: https://github.com/mm/heartbridge
Author: Matthew Mascioni
Author-email: mascionim@gmail.com
License: UNKNOWN
Keywords: heartrate apple watch shortcuts ios health
Platform: UNKNOWN
Classifier: Development Status :: 5 - Production/Stable
Classifier: Natural Language :: English
Classifier: Environment :: Console
Classifier: License :: OSI Approved :: MIT License
Classifier: Programming Language :: Python :: 3.8
Classifier: Programming Language :: Python :: 3.9
Requires-Python: >=3.8
Requires-Dist: uvicorn
Requires-Dist: starlette
